SFM4300_readout/SensorInterface.py
SFM4300_readout/__init__.py
SFM4300_readout-0.1.2.dist-info/LICENSE
SFM4300_readout-0.1.2.dist-info/METADATA
SFM4300_readout-0.1.2.dist-info/WHEEL
SFM4300_readout-0.1.2.dist-info/top_level.txt
SFM4300_readout-0.1.2.dist-info/RECORD
